{
  "pause": {},
  "force_next": "bolt",
  "interval_override": {},
  "session_manager": {},
  "last_bolt_commit_cycle": 3101,
  "paused_at_bolt_cycle": 3097,
  "notes": "C3102 Lead: ROOT CAUSE FOUND for task #100 lightbox (16 failed attempts). product-gallery.tsx lines 542-543 have TWO style={{}} props on same div — JSX silently drops first (sizing: width/height/maxWidth). Container has NO dimensions → image unpositioned on mobile. FIX: merge both style objects into one. Bolt unpaused + force_next. Sage/Trace wait for commit. Feedback #1203 ACK.",
  "schema": {
    "pause": "Map of agent_name to condition (paused or until_next_bolt_commit or until_lead_directive)",
    "force_next": "Agent name to force as next scheduled, or null. Cleared after use.",
    "interval_override": "Map of agent_name to run_every integer",
    "session_manager": {
      "kill_zombie_tasks": "bool",
      "deploy_now": "bool",
      "requeue_failed": "list of task IDs",
      "reset_no_change_counter": "bool"
    }
  },
  "session_manager_last_processed": "2026-04-10T15:37:05.651881"
}